LICENSE
MANIFEST.in
README.rst
setup.py
nacha/__init__.py
py_nacha.egg-info/PKG-INFO
py_nacha.egg-info/SOURCES.txt
py_nacha.egg-info/dependency_links.txt
py_nacha.egg-info/requires.txt
py_nacha.egg-info/top_level.txt