Metadata-Version: 1.1
Name: py-nacha
Version: 0.1.2
Summary: NACHA File Generation
Home-page: https://github.com/DisruptiveLabs/nacha
Author: DisruptiveLabs
Author-email: team+nacha@comanage.com
License: UNKNOWN
Platform: any
Classifier: Development Status :: 4 - Beta
Classifier: Intended Audience :: Developers
Classifier: Natural Language :: English
Classifier: License :: OSI Approved :: ISC License (ISCL)
Classifier: Programming Language :: Python
Classifier: Programming Language :: Python :: 2.7
